{"cameraMode":{"drawMode":0,"name":"Shaded","section":"Shading Mode"},"sceneLighting":true,"audioPlay":false,"sceneViewState":{"m_AlwaysRefresh":false,"showFog":true,"showSkybox":true,"showFlares":true,"showImageEffects":true,"showParticleSystems":true,"showVisualEffectGraphs":true,"m_FxEnabled":true},"in2DMode":false,"pivot":{"x":13.029447555541993,"y":11.411474227905274,"z":13.801982879638672},"rotation":{"x":-0.20235727727413178,"y":-0.17895276844501496,"z":0.03763921558856964,"w":-0.9620887637138367},"size":29.7166748046875,"orthographic":false}